python_aid-0.2.2.dist-info/METADATA
python_aid-0.2.2.dist-info/WHEEL
python_aid-0.2.2.dist-info/entry_points.txt
python_aid-0.2.2.dist-info/licenses/LICENSE
python_aid/__init__.py
python_aid/aid.py
python_aid/aidx.py
python_aid/base36.py
python_aid-0.2.2.dist-info/RECORD
