Metadata-Version: 2.1
Name: python-aid
Version: 0.2.2
Summary: python-aidはMisskeyのaid/aidxのPython向けの実装です。
Author-Email: AmaseCocoa <amase.cocoa@gmail.com>
License: MIT
Project-URL: Repository, https://github.com/AmaseCocoa/python-aid.git
Requires-Python: >=3.9
